ragbooster-0.1.1.dist-info/METADATA
ragbooster-0.1.1.dist-info/WHEEL
ragbooster-0.1.1.dist-info/license_files/LICENSE
ragbooster/core.py
ragbooster/tuning.py
ragbooster/__init__.py
ragbooster/demo.py
ragbooster/rag.py
ragbooster/retriever.py
ragbooster/generator.py
ragbooster/ragbooster.cpython-311-i386-linux-gnu.so
ragbooster-0.1.1.dist-info/RECORD
